magg/__init__.py
magg/__main__.py
magg/auth.py
magg/cli.py
magg/client.py
magg/kit.py
magg/messaging.py
magg/process.py
magg/reload.py
magg/settings.py
magg/contrib/magg.mbro
magg/contrib/readme.md
magg/contrib/kit.d/example.json
magg/discovery/__init__.py
magg/discovery/catalog.py
magg/discovery/metadata.py
magg/discovery/search.py
magg/logs/__init__.py
magg/logs/adapter.py
magg/logs/config.py
magg/logs/defaults.py
magg/logs/filter.py
magg/logs/formatter.py
magg/logs/handler.py
magg/logs/listener.py
magg/logs/queue.py
magg/mbro/__init__.py
magg/mbro/__main__.py
magg/mbro/arepl.py
magg/mbro/cli.py
magg/mbro/client.py
magg/mbro/command.py
magg/mbro/completers.py
magg/mbro/formatter.py
magg/mbro/multiline.py
magg/mbro/parser.py
magg/mbro/scripts.py
magg/mbro/validator.py
magg/proxy/__init__.py
magg/proxy/client.py
magg/proxy/mixin.py
magg/proxy/server.py
magg/proxy/types.py
magg/server/__init__.py
magg/server/defaults.py
magg/server/manager.py
magg/server/response.py
magg/server/runner.py
magg/server/server.py
magg/util/__init__.py
magg/util/paths.py
magg/util/stdio_patch.py
magg/util/system.py
magg/util/terminal.py
magg/util/transform.py
magg/util/transport.py
magg/util/transports.py
magg/util/uri.py
magg-0.10.1.dist-info/METADATA
magg-0.10.1.dist-info/WHEEL
magg-0.10.1.dist-info/entry_points.txt
magg-0.10.1.dist-info/licenses/license.md
magg-0.10.1.dist-info/RECORD
