Metadata-Version: 2.4
Name: magg
Version: 0.10.1
Summary: MCP Aggregator
Project-URL: Homepage, https://github.com/sitbon/magg
Project-URL: Repository, https://github.com/sitbon/magg.git
Project-URL: Documentation, https://github.com/sitbon/magg#readme
Project-URL: Issues, https://github.com/sitbon/magg/issues
Project-URL: Release Notes, https://github.com/sitbon/magg/releases
Author-email: Phillip Sitbon <phillip.sitbon@gmail.com>
License: AGPL-3.0-or-later
License-File: license.md
Keywords: agent,aggregator,ai,aiohttp,context,fastmcp,mcp,model,protocol,proxy,pydantic,pydantic-settings,rich
Classifier: Development Status :: 4 - Beta
Classifier: Environment :: Web Environment
Classifier: Intended Audience :: Developers
Classifier: License :: OSI Approved :: GNU Affero General Public License v3 or later (AGPLv3+)
Classifier: Natural Language :: English
Classifier: Operating System :: OS Independent
Classifier: Programming Language :: Python :: 3 :: Only
Classifier: Programming Language :: Python :: 3.12
Classifier: Programming Language :: Python :: 3.13
Classifier: Programming Language :: Python :: Implementation :: CPython
Classifier: Topic :: Internet :: Proxy Servers
Classifier: Topic :: Internet :: WWW/HTTP :: Dynamic Content
Classifier: Topic :: Internet :: WWW/HTTP :: HTTP Servers
Classifier: Topic :: Software Development :: Libraries
Classifier: Topic :: Software Development :: Libraries :: Python Modules
Requires-Python: >=3.12
Requires-Dist: aiohttp>=3.12.13
Requires-Dist: art>=6.5
Requires-Dist: cryptography>=45.0.4
Requires-Dist: fastmcp>=2.8.0
Requires-Dist: prompt-toolkit>=3.0.51
Requires-Dist: pydantic-settings>=2.10.0
Requires-Dist: pydantic>=2.11.7
Requires-Dist: pyjwt>=2.10.1
Requires-Dist: rich>=14.0.0
Requires-Dist: watchdog>=6.0.0
Provides-Extra: test
Requires-Dist: pytest-asyncio>=1.0.0; extra == 'test'
Requires-Dist: pytest>=8.4.0; extra == 'test'
